schedule/__init__.py
schedule/py.typed
schedule-1.2.2.dist-info/AUTHORS.rst
schedule-1.2.2.dist-info/LICENSE.txt
schedule-1.2.2.dist-info/METADATA
schedule-1.2.2.dist-info/WHEEL
schedule-1.2.2.dist-info/top_level.txt
schedule-1.2.2.dist-info/RECORD
